[{"id":"L NORRIS","abbreviation":"NOR","first_name":"Lando","last_name":"Norris","country_alpha3":"GBR"},{"id":"P GASLY","abbreviation":"GAS","first_name":"Pierre","last_name":"Gasly","country_alpha3":"FRA"},{"id":"S PEREZ","abbreviation":"PER","first_name":"Sergio","last_name":"Perez","country_alpha3":"MEX"},{"id":"F ALONSO","abbreviation":"ALO","first_name":"Fernando","last_name":"Alonso","country_alpha3":"ESP"},{"id":"C LECLERC","abbreviation":"LEC","first_name":"Charles","last_name":"Leclerc","country_alpha3":"MON"},{"id":"K MAGNUSSEN","abbreviation":"MAG","first_name":"Kevin","last_name":"Magnussen","country_alpha3":"DEN"},{"id":"G ZHOU","abbreviation":"ZHO","first_name":"Guanyu","last_name":"Zhou","country_alpha3":"CHN"},{"id":"N HULKENBERG","abbreviation":"HUL","first_name":"Nico","last_name":"Hulkenberg","country_alpha3":"GER"},{"id":"R HIRAKAWA","abbreviation":"HIR","first_name":"Ryo","last_name":"Hirakawa","country_alpha3":"JPN"},{"id":"L LAWSON","abbreviation":"LAW","first_name":"Liam","last_name":"Lawson","country_alpha3":"NZL"},{"id":"F DRUGOVICH","abbreviation":"DRU","first_name":"Felipe","last_name":"Drugovich","country_alpha3":"BRA"},{"id":"I HADJAR","abbreviation":"HAD","first_name":"Isack","last_name":"Hadjar","country_alpha3":"FRA"},{"id":"A LECLERC","abbreviation":"LEL","first_name":"Arthur","last_name":"Leclerc","country_alpha3":"MON"},{"id":"A IWASA","abbreviation":"IWA","first_name":"Ayumu","last_name":"Iwasa","country_alpha3":"JPN"},{"id":"F COLAPINTO","abbreviation":"COL","first_name":"Franco","last_name":"Colapinto","country_alpha3":"ARG"},{"id":"L HAMILTON","abbreviation":"HAM","first_name":"Lewis","last_name":"Hamilton","country_alpha3":"GBR"},{"id":"L BROWNING","abbreviation":"BRO","first_name":"Luke","last_name":"Browning","country_alpha3":"GBR"},{"id":"J DOOHAN","abbreviation":"DOO","first_name":"Jack","last_name":"Doohan","country_alpha3":"AUS"},{"id":"G RUSSELL","abbreviation":"RUS","first_name":"George","last_name":"Russell","country_alpha3":"GBR"},{"id":"V BOTTAS","abbreviation":"BOT","first_name":"Valtteri","last_name":"Bottas","country_alpha3":"FIN"}]